{ "compressionlevel":-1,
 "editorsettings":
    {
     "chunksize":
        {
         "height":32,
         "width":32
        }
    },
 "height":22,
 "infinite":false,
 "layers":[
        {
         "color":"#000000",
         "draworder":"topdown",
         "id":8,
         "name":"solid-layer",
         "objects":[
                {
                 "height":64,
                 "id":79,
                 "name":"",
                 "rotation":0,
                 "type":"",
                 "visible":true,
                 "width":1312,
                 "x":0,
                 "y":0
                }, 
                {
                 "height":64,
                 "id":81,
                 "name":"",
                 "rotation":0,
                 "type":"",
                 "visible":true,
                 "width":224,
                 "x":1088,
                 "y":64
                }, 
                {
                 "height":0,
                 "id":82,
                 "name":"",
                 "polygon":[
                        {
                         "x":0,
                         "y":0
                        }, 
                        {
                         "x":-64,
                         "y":-160
                        }, 
                        {
                         "x":0,
                         "y":-160
                        }],
                 "rotation":0,
                 "type":"",
                 "visible":true,
                 "width":0,
                 "x":1088,
                 "y":224
                }, 
                {
                 "height":0,
                 "id":83,
                 "name":"",
                 "polygon":[
                        {
                         "x":0,
                         "y":0
                        }, 
                        {
                         "x":-32,
                         "y":96
                        }, 
                        {
                         "x":-32,
                         "y":0
                        }],
                 "rotation":0,
                 "type":"",
                 "visible":true,
                 "width":0,
                 "x":1120,
                 "y":128
                }, 
                {
                 "height":0,
                 "id":86,
                 "name":"",
                 "polygon":[
                        {
                         "x":0,
                         "y":0
                        }, 
                        {
                         "x":320,
                         "y":0
                        }, 
                        {
                         "x":320,
                         "y":192
                        }, 
                        {
                         "x":288,
                         "y":384
                        }, 
                        {
                         "x":0,
                         "y":384
                        }],
                 "rotation":0,
                 "type":"",
                 "visible":true,
                 "width":0,
                 "x":0,
                 "y":64
                }, 
                {
                 "height":0,
                 "id":87,
                 "name":"",
                 "polygon":[
                        {
                         "x":0,
                         "y":0
                        }, 
                        {
                         "x":-32,
                         "y":96
                        }, 
                        {
                         "x":-32,
                         "y":160
                        }, 
                        {
                         "x":192,
                         "y":160
                        }, 
                        {
                         "x":192,
                         "y":0
                        }],
                 "rotation":0,
                 "type":"",
                 "visible":true,
                 "width":0,
                 "x":1120,
                 "y":544
                }, 
                {
                 "height":64,
                 "id":89,
                 "name":"",
                 "rotation":0,
                 "type":"",
                 "visible":true,
                 "width":1088,
                 "x":0,
                 "y":640
                }, 
                {
                 "height":96,
                 "id":90,
                 "name":"",
                 "rotation":0,
                 "type":"",
                 "visible":true,
                 "width":576,
                 "x":0,
                 "y":544
                }, 
                {
                 "height":96,
                 "id":91,
                 "name":"",
                 "rotation":0,
                 "type":"",
                 "visible":true,
                 "width":64,
                 "x":0,
                 "y":448
                }, 
                {
                 "height":416,
                 "id":92,
                 "name":"",
                 "rotation":0,
                 "type":"",
                 "visible":true,
                 "width":32,
                 "x":1280,
                 "y":128
                }, 
                {
                 "height":32,
                 "id":93,
                 "name":"",
                 "rotation":0,
                 "type":"",
                 "visible":true,
                 "width":64,
                 "x":992,
                 "y":448
                }],
         "opacity":1,
         "type":"objectgroup",
         "visible":true,
         "x":0,
         "y":0
        }, 
        {
         "draworder":"topdown",
         "id":2,
         "name":"object-layer",
         "objects":[
                {
                 "height":0,
                 "id":41,
                 "name":"manna",
                 "point":true,
                 "rotation":0,
                 "type":"",
                 "visible":true,
                 "width":0,
                 "x":832,
                 "y":616
                }, 
                {
                 "height":0,
                 "id":76,
                 "name":"manna",
                 "point":true,
                 "rotation":0,
                 "type":"",
                 "visible":true,
                 "width":0,
                 "x":1264,
                 "y":336
                }, 
                {
                 "height":0,
                 "id":78,
                 "name":"manna",
                 "point":true,
                 "rotation":0,
                 "type":"",
                 "visible":true,
                 "width":0,
                 "x":1264,
                 "y":304
                }, 
                {
                 "height":0,
                 "id":77,
                 "name":"manna",
                 "point":true,
                 "rotation":0,
                 "type":"",
                 "visible":true,
                 "width":0,
                 "x":1264,
                 "y":368
                }, 
                {
                 "height":0,
                 "id":13,
                 "name":"player",
                 "point":true,
                 "rotation":0,
                 "type":"",
                 "visible":true,
                 "width":0,
                 "x":144,
                 "y":544
                }, 
                {
                 "height":0,
                 "id":17,
                 "name":"key",
                 "point":true,
                 "properties":[
                        {
                         "name":"ForDoor",
                         "type":"int",
                         "value":1
                        }],
                 "rotation":0,
                 "type":"",
                 "visible":true,
                 "width":0,
                 "x":1024,
                 "y":432
                }, 
                {
                 "height":0,
                 "id":31,
                 "name":"door",
                 "point":true,
                 "properties":[
                        {
                         "name":"DoorId",
                         "type":"int",
                         "value":1
                        }, 
                        {
                         "name":"IsOpen",
                         "type":"bool",
                         "value":false
                        }, 
                        {
                         "name":"LeadsTo",
                         "type":"string",
                         "value":"map4.json"
                        }],
                 "rotation":0,
                 "type":"",
                 "visible":true,
                 "width":0,
                 "x":464,
                 "y":544
                }, 
                {
                 "height":16,
                 "id":62,
                 "name":"spike",
                 "rotation":0,
                 "type":"",
                 "visible":true,
                 "width":32,
                 "x":640,
                 "y":624
                }, 
                {
                 "height":16,
                 "id":71,
                 "name":"spike",
                 "rotation":0,
                 "type":"",
                 "visible":true,
                 "width":32,
                 "x":672,
                 "y":624
                }, 
                {
                 "height":16,
                 "id":75,
                 "name":"spike",
                 "rotation":0,
                 "type":"",
                 "visible":true,
                 "width":32,
                 "x":992,
                 "y":624
                }, 
                {
                 "height":16,
                 "id":72,
                 "name":"spike",
                 "rotation":0,
                 "type":"",
                 "visible":true,
                 "width":32,
                 "x":1056,
                 "y":624
                }, 
                {
                 "height":16,
                 "id":73,
                 "name":"spike",
                 "rotation":0,
                 "type":"",
                 "visible":true,
                 "width":32,
                 "x":1024,
                 "y":624
                }, 
                {
                 "height":0,
                 "id":69,
                 "name":"missile-turret",
                 "point":true,
                 "rotation":0,
                 "type":"",
                 "visible":true,
                 "width":0,
                 "x":368,
                 "y":120
                }, 
                {
                 "height":0,
                 "id":70,
                 "name":"missile-turret",
                 "point":true,
                 "rotation":0,
                 "type":"",
                 "visible":true,
                 "width":0,
                 "x":1152,
                 "y":160
                }, 
                {
                 "height":16,
                 "id":94,
                 "name":"spike",
                 "rotation":0,
                 "type":"",
                 "visible":true,
                 "width":32,
                 "x":608,
                 "y":624
                }, 
                {
                 "height":16,
                 "id":95,
                 "name":"spike",
                 "rotation":0,
                 "type":"",
                 "visible":true,
                 "width":32,
                 "x":576,
                 "y":624
                }, 
                {
                 "height":16,
                 "id":96,
                 "name":"spike",
                 "rotation":0,
                 "type":"",
                 "visible":true,
                 "width":32,
                 "x":960,
                 "y":624
                }],
         "opacity":1,
         "type":"objectgroup",
         "visible":true,
         "x":0,
         "y":0
        }],
 "nextlayerid":9,
 "nextobjectid":97,
 "orientation":"orthogonal",
 "renderorder":"right-down",
 "tiledversion":"1.11.2",
 "tileheight":32,
 "tilesets":[
        {
         "columns":8,
         "firstgid":1,
         "image":"..\/tilesets\/tileset-simple-32x32.png",
         "imageheight":192,
         "imagewidth":256,
         "margin":0,
         "name":"tileset",
         "spacing":0,
         "tilecount":48,
         "tileheight":32,
         "tilerendersize":"grid",
         "tiles":[
                {
                 "id":0,
                 "objectgroup":
                    {
                     "draworder":"index",
                     "name":"",
                     "objects":[
                            {
                             "height":32,
                             "id":1,
                             "name":"",
                             "rotation":0,
                             "type":"",
                             "visible":true,
                             "width":32,
                             "x":0,
                             "y":0
                            }],
                     "opacity":1,
                     "type":"objectgroup",
                     "visible":true,
                     "x":0,
                     "y":0
                    }
                }],
         "tilewidth":32
        }],
 "tilewidth":32,
 "type":"map",
 "version":"1.10",
 "width":41
}