{ "compressionlevel":-1,
 "editorsettings":
    {
     "chunksize":
        {
         "height":32,
         "width":32
        }
    },
 "height":28,
 "infinite":false,
 "layers":[
        {
         "color":"#000000",
         "draworder":"topdown",
         "id":8,
         "name":"solid-layer",
         "objects":[
                {
                 "height":480,
                 "id":47,
                 "name":"",
                 "rotation":0,
                 "type":"",
                 "visible":true,
                 "width":32,
                 "x":736,
                 "y":320
                }, 
                {
                 "height":480,
                 "id":48,
                 "name":"",
                 "rotation":0,
                 "type":"",
                 "visible":true,
                 "width":32,
                 "x":864,
                 "y":320
                }, 
                {
                 "height":192,
                 "id":49,
                 "name":"",
                 "rotation":0,
                 "type":"",
                 "visible":true,
                 "width":32,
                 "x":1376,
                 "y":416
                }, 
                {
                 "height":0,
                 "id":51,
                 "name":"",
                 "polygon":[
                        {
                         "x":0,
                         "y":0
                        }, 
                        {
                         "x":-32,
                         "y":-32
                        }, 
                        {
                         "x":64,
                         "y":-32
                        }, 
                        {
                         "x":32,
                         "y":0
                        }],
                 "rotation":0,
                 "type":"",
                 "visible":true,
                 "width":0,
                 "x":224,
                 "y":544
                }, 
                {
                 "height":864,
                 "id":52,
                 "name":"",
                 "rotation":0,
                 "type":"",
                 "visible":true,
                 "width":32,
                 "x":0,
                 "y":0
                }, 
                {
                 "height":32,
                 "id":53,
                 "name":"",
                 "rotation":0,
                 "type":"",
                 "visible":true,
                 "width":1632,
                 "x":0,
                 "y":864
                }, 
                {
                 "height":864,
                 "id":54,
                 "name":"",
                 "rotation":0,
                 "type":"",
                 "visible":true,
                 "width":32,
                 "x":1600,
                 "y":0
                }, 
                {
                 "height":32,
                 "id":55,
                 "name":"",
                 "rotation":0,
                 "type":"",
                 "visible":true,
                 "width":1568,
                 "x":32,
                 "y":0
                }],
         "opacity":1,
         "type":"objectgroup",
         "visible":true,
         "x":0,
         "y":0
        }, 
        {
         "draworder":"topdown",
         "id":2,
         "name":"object-layer",
         "objects":[
                {
                 "height":0,
                 "id":13,
                 "name":"player",
                 "point":true,
                 "rotation":0,
                 "type":"",
                 "visible":true,
                 "width":0,
                 "x":240,
                 "y":864
                }, 
                {
                 "height":0,
                 "id":17,
                 "name":"key",
                 "point":true,
                 "properties":[
                        {
                         "name":"ForDoor",
                         "type":"int",
                         "value":1
                        }],
                 "rotation":0,
                 "type":"",
                 "visible":true,
                 "width":0,
                 "x":1360,
                 "y":520
                }, 
                {
                 "height":0,
                 "id":31,
                 "name":"door",
                 "point":true,
                 "properties":[
                        {
                         "name":"DoorId",
                         "type":"int",
                         "value":1
                        }, 
                        {
                         "name":"IsOpen",
                         "type":"bool",
                         "value":false
                        }, 
                        {
                         "name":"LeadsTo",
                         "type":"string",
                         "value":"map6.json"
                        }],
                 "rotation":0,
                 "type":"",
                 "visible":true,
                 "width":0,
                 "x":240,
                 "y":512
                }, 
                {
                 "height":32,
                 "id":36,
                 "name":"jump-pad",
                 "rotation":0,
                 "type":"",
                 "visible":true,
                 "width":32,
                 "x":800,
                 "y":832
                }],
         "opacity":1,
         "type":"objectgroup",
         "visible":true,
         "x":0,
         "y":0
        }],
 "nextlayerid":9,
 "nextobjectid":56,
 "orientation":"orthogonal",
 "renderorder":"right-down",
 "tiledversion":"1.11.2",
 "tileheight":32,
 "tilesets":[
        {
         "columns":8,
         "firstgid":1,
         "image":"..\/tilesets\/tileset-simple-32x32.png",
         "imageheight":192,
         "imagewidth":256,
         "margin":0,
         "name":"tileset",
         "spacing":0,
         "tilecount":48,
         "tileheight":32,
         "tilerendersize":"grid",
         "tiles":[
                {
                 "id":0,
                 "objectgroup":
                    {
                     "draworder":"index",
                     "name":"",
                     "objects":[
                            {
                             "height":32,
                             "id":1,
                             "name":"",
                             "rotation":0,
                             "type":"",
                             "visible":true,
                             "width":32,
                             "x":0,
                             "y":0
                            }],
                     "opacity":1,
                     "type":"objectgroup",
                     "visible":true,
                     "x":0,
                     "y":0
                    }
                }],
         "tilewidth":32
        }],
 "tilewidth":32,
 "type":"map",
 "version":"1.10",
 "width":51
}